randseal/__init__.py
randseal/client.py
randseal/errors.py
randseal/timestamp.py
randseal/vars.py
randseal/archive/__init__.py
randseal/archive/one.py
randseal-3.3.1.dist-info/LICENCE
randseal-3.3.1.dist-info/METADATA
randseal-3.3.1.dist-info/WHEEL
randseal-3.3.1.dist-info/top_level.txt
randseal-3.3.1.dist-info/RECORD
