Metadata-Version: 2.1
Name: randseal
Version: 3.3.1
Summary: Generates random seal images for discord.py or py-cord
Home-page: https://github.com/mariohero24/randseal
Author: Guard Boi
Author-email: guard@cowbot.xyz
Classifier: Programming Language :: Python :: 3
Classifier: License :: OSI Approved :: MIT License
Classifier: Operating System :: OS Independent
Requires-Python: >=3.8
License-File: LICENCE
